[
{
  "model": "tracker.issue",
  "pk": 2,
  "fields": {
    "summary": "Bug # 1",
    "description": "Lorem ipsum dolor, sit amet consectetur adipisicing elit. Voluptatum neque et quos sed corporis tenetur dolore saepe numquam asperiores aliquid eum error, voluptatem repellendus, fugit laboriosam magni, atque harum omnis.",
    "status": 2,
    "created_at": "2021-03-10T10:33:24.450Z",
    "updated_at": "2021-03-29T10:46:49.857Z",
    "project": 1,
    "type": [
      2,
      3
    ]
  }
},
{
  "model": "tracker.issue",
  "pk": 3,
  "fields": {
    "summary": "Bug #2",
    "description": "Lorem ipsum dolor, sit amet consectetur adipisicing elit. Voluptatum neque et quos sed corporis tenetur dolore saepe numquam asperiores aliquid eum error, voluptatem repellendus, fugit laboriosam magni, atque harum omnis.",
    "status": 3,
    "created_at": "2021-03-10T10:33:35.951Z",
    "updated_at": "2021-04-01T12:39:03.451Z",
    "project": 1,
    "type": [
      1
    ]
  }
},
{
  "model": "tracker.issue",
  "pk": 4,
  "fields": {
    "summary": "Enhancement #1",
    "description": "Lorem ipsum dolor, sit amet consectetur adipisicing elit. Voluptatum neque et quos sed corporis tenetur dolore saepe numquam asperiores aliquid eum error, voluptatem repellendus, fugit laboriosam magni, atque harum omnis.",
    "status": 1,
    "created_at": "2021-03-10T10:34:03.793Z",
    "updated_at": "2021-03-22T10:50:38.569Z",
    "project": 1,
    "type": [
      2,
      3
    ]
  }
},
{
  "model": "tracker.issue",
  "pk": 5,
  "fields": {
    "summary": "Enhancement #2",
    "description": "Lorem ipsum dolor, sit amet consectetur adipisicing elit. Voluptatum neque et quos sed corporis tenetur dolore saepe numquam asperiores aliquid eum error, voluptatem repellendus, fugit laboriosam magni, atque harum omnis.",
    "status": 2,
    "created_at": "2021-03-10T10:34:22.523Z",
    "updated_at": "2021-03-22T10:50:19.086Z",
    "project": 1,
    "type": [
      1,
      2
    ]
  }
},
{
  "model": "tracker.issue",
  "pk": 29,
  "fields": {
    "summary": "Enhancement 3",
    "description": "Enhancement 3",
    "status": 1,
    "created_at": "2021-03-20T17:11:51.440Z",
    "updated_at": "2021-03-22T10:22:45.301Z",
    "project": 1,
    "type": [
      2
    ]
  }
},
{
  "model": "tracker.issue",
  "pk": 30,
  "fields": {
    "summary": "Task #1",
    "description": "Task 1",
    "status": 1,
    "created_at": "2021-03-22T10:18:16.573Z",
    "updated_at": "2021-03-22T10:50:50.120Z",
    "project": 1,
    "type": [
      1
    ]
  }
},
{
  "model": "tracker.issue",
  "pk": 31,
  "fields": {
    "summary": "Task #2",
    "description": "Task 2",
    "status": 2,
    "created_at": "2021-03-22T10:18:33.929Z",
    "updated_at": "2021-03-22T10:50:55.333Z",
    "project": 1,
    "type": [
      1
    ]
  }
},
{
  "model": "tracker.issue",
  "pk": 38,
  "fields": {
    "summary": "Task 1",
    "description": "Task 1",
    "status": 2,
    "created_at": "2021-03-30T14:02:38.817Z",
    "updated_at": "2021-03-30T14:02:38.817Z",
    "project": 2,
    "type": [
      1
    ]
  }
},
{
  "model": "tracker.issue",
  "pk": 39,
  "fields": {
    "summary": "Bug 2",
    "description": "Bug 2",
    "status": 1,
    "created_at": "2021-03-30T14:04:28.836Z",
    "updated_at": "2021-03-30T14:04:28.836Z",
    "project": 2,
    "type": [
      2,
      3
    ]
  }
},
{
  "model": "tracker.issue",
  "pk": 40,
  "fields": {
    "summary": "Bug 333",
    "description": "Bug 333",
    "status": 1,
    "created_at": "2021-03-30T14:07:02.459Z",
    "updated_at": "2021-03-30T14:07:02.459Z",
    "project": 2,
    "type": [
      3
    ]
  }
},
{
  "model": "tracker.issue",
  "pk": 41,
  "fields": {
    "summary": "Task 22",
    "description": "Task 22",
    "status": 1,
    "created_at": "2021-03-30T14:11:27.504Z",
    "updated_at": "2021-04-01T12:25:39.781Z",
    "project": 2,
    "type": [
      3
    ]
  }
},
{
  "model": "tracker.issue",
  "pk": 49,
  "fields": {
    "summary": "issue 19",
    "description": "Issue 19",
    "status": 2,
    "created_at": "2021-04-01T12:22:41.408Z",
    "updated_at": "2021-04-01T12:22:41.408Z",
    "project": 8,
    "type": [
      1
    ]
  }
},
{
  "model": "tracker.issue",
  "pk": 52,
  "fields": {
    "summary": "test",
    "description": "gvhbjk",
    "status": 2,
    "created_at": "2021-04-15T09:00:01.667Z",
    "updated_at": "2021-04-15T09:00:01.667Z",
    "project": 13,
    "type": [
      2
    ]
  }
},
{
  "model": "tracker.status",
  "pk": 1,
  "fields": {
    "name": "New"
  }
},
{
  "model": "tracker.status",
  "pk": 2,
  "fields": {
    "name": "In Progress"
  }
},
{
  "model": "tracker.status",
  "pk": 3,
  "fields": {
    "name": "Done"
  }
},
{
  "model": "tracker.type",
  "pk": 1,
  "fields": {
    "name": "Task"
  }
},
{
  "model": "tracker.type",
  "pk": 2,
  "fields": {
    "name": "Enhancement"
  }
},
{
  "model": "tracker.type",
  "pk": 3,
  "fields": {
    "name": "Bug"
  }
},
{
  "model": "tracker.project",
  "pk": 1,
  "fields": {
    "name": "First Project",
    "description": "This is the first project. Good luck!",
    "start_date": "2021-03-29",
    "end_date": null,
    "user": [
      1,
      17,
      18,
      20
    ]
  }
},
{
  "model": "tracker.project",
  "pk": 2,
  "fields": {
    "name": "Project 2",
    "description": "This is project # 2",
    "start_date": "2021-03-29",
    "end_date": null,
    "user": [
      17,
      18,
      20
    ]
  }
},
{
  "model": "tracker.project",
  "pk": 8,
  "fields": {
    "name": "Project 10",
    "description": "This is project # 10",
    "start_date": "2021-03-29",
    "end_date": null,
    "user": [
      1,
      19,
      20
    ]
  }
},
{
  "model": "tracker.project",
  "pk": 9,
  "fields": {
    "name": "Project 11",
    "description": "This is project # 11",
    "start_date": "2021-03-08",
    "end_date": null,
    "user": [
      1
    ]
  }
},
{
  "model": "tracker.project",
  "pk": 10,
  "fields": {
    "name": "Jupiter",
    "description": "This is project Jupiter",
    "start_date": "2021-03-29",
    "end_date": null,
    "user": []
  }
},
{
  "model": "tracker.project",
  "pk": 11,
  "fields": {
    "name": "Anaconda",
    "description": "This is project Anaconda",
    "start_date": "2021-03-29",
    "end_date": null,
    "user": []
  }
},
{
  "model": "tracker.project",
  "pk": 12,
  "fields": {
    "name": "Project X",
    "description": "This is project X",
    "start_date": "2021-03-29",
    "end_date": null,
    "user": [
      1
    ]
  }
},
{
  "model": "tracker.project",
  "pk": 13,
  "fields": {
    "name": "Project 10",
    "description": "This is project 10",
    "start_date": "2021-03-08",
    "end_date": null,
    "user": []
  }
},
{
  "model": "tracker.project",
  "pk": 14,
  "fields": {
    "name": "Test project",
    "description": "This is test project",
    "start_date": "2021-03-12",
    "end_date": null,
    "user": [
      1,
      19
    ]
  }
},
{
  "model": "tracker.project",
  "pk": 15,
  "fields": {
    "name": "Hello",
    "description": "hello2",
    "start_date": "2021-03-29",
    "end_date": "2021-04-09",
    "user": [
      17
    ]
  }
},
{
  "model": "accounts.profile",
  "pk": 1,
  "fields": {
    "user": 1,
    "avatar": "user_pics/beautiful-latin-woman-avatar-character-icon-free-vector.jpg",
    "info": "HI! I am an admin of this tracker website!",
    "github": "https://github.com/UuljanAitnazarova"
  }
},
{
  "model": "accounts.profile",
  "pk": 2,
  "fields": {
    "user": 21,
    "avatar": "",
    "info": null,
    "github": null
  }
},
{
  "model": "accounts.profile",
  "pk": 3,
  "fields": {
    "user": 17,
    "avatar": "user_pics/images.png",
    "info": "Hi! I am Jenny - the best PM!",
    "github": null
  }
},
{
  "model": "accounts.profile",
  "pk": 4,
  "fields": {
    "user": 18,
    "avatar": "user_pics/man5-512.png",
    "info": "Hey! I am Tom!",
    "github": null
  }
},
{
  "model": "accounts.profile",
  "pk": 5,
  "fields": {
    "user": 19,
    "avatar": "",
    "info": null,
    "github": null
  }
},
{
  "model": "accounts.profile",
  "pk": 6,
  "fields": {
    "user": 20,
    "avatar": "user_pics/businesswoman-woman-female-icon_24877-11464.jpeg",
    "info": "I am Jess!",
    "github": null
  }
},
{
  "model": "accounts.profile",
  "pk": 7,
  "fields": {
    "user": 22,
    "avatar": "",
    "info": null,
    "github": null
  }
}
]
